tgcli/__init__.py
tgcli/__main__.py
tgcli/commands/__init__.py
tgcli/commands/app.py
tgcli/commands/config/__init__.py
tgcli/commands/config/add.py
tgcli/commands/config/app.py
tgcli/commands/config/delete.py
tgcli/commands/config/describe.py
tgcli/commands/config/list.py
tgcli/commands/delete/__init__.py
tgcli/commands/delete/app.py
tgcli/commands/etc/__init__.py
tgcli/commands/etc/help_text.py
tgcli/commands/get/__init__.py
tgcli/commands/get/app.py
tgcli/commands/gsql/__init__.py
tgcli/commands/gsql/app.py
tgcli/commands/load/__init__.py
tgcli/commands/load/app.py
tgcli/commands/util.py
tgcli/tigergraph/__init__.py
tgcli/tigergraph/common.py
tgcli/util/__init__.py
tgcli/util/cli.py
tgcli/util/io.py
tgcli/util/tgcli_config.py
tigergraphcli-0.0.2.1.dist-info/entry_points.txt
tigergraphcli-0.0.2.1.dist-info/LICENSE
tigergraphcli-0.0.2.1.dist-info/WHEEL
tigergraphcli-0.0.2.1.dist-info/METADATA
tigergraphcli-0.0.2.1.dist-info/RECORD
