Metadata-Version: 2.1
Name: tigergraphcli
Version: 0.0.2.1
Summary: CLI for TigerGraph
Home-page: https://github.com/frankfka/TigerGraphCLI
License: MIT
Keywords: TigerGraph,CLI,pyTigerGraph,Graph Database
Author: Frank Jia
Author-email: jiafrank98@gmail.com
Requires-Python: >=3.7,<4.0
Classifier: License :: OSI Approved :: MIT License
Classifier: Programming Language :: Python :: 3
Classifier: Programming Language :: Python :: 3.7
Classifier: Programming Language :: Python :: 3.8
Requires-Dist: pyTigerGraph (>=0.0.7,<0.0.8)
Requires-Dist: typer (>=0.3.1,<0.4.0)
Project-URL: Documentation, https://github.com/frankfka/TigerGraphCLI
